nv_sgl-0.15.0.dist-info/licenses/LICENSE
sgl/__init__.py
sgl/__init__.pyi
sgl/dxcompiler.dll
sgl/dxil.dll
sgl/sgl.dll
sgl/sgl_ext.cp39-win_amd64.pyd
sgl/slang-glslang.dll
sgl/slang-llvm.dll
sgl/slang-rt.dll
sgl/slang.dll
sgl/D3D12/D3D12Core.dll
sgl/D3D12/d3d12SDKLayers.dll
sgl/include/slang-deprecated.h
sgl/include/slang-image-format-defs.h
sgl/include/slang-rhi-config.h
sgl/include/slang-rhi.h
sgl/include/slang-user-config.h
sgl/include/slang.h
sgl/include/sgl/sgl.h
sgl/include/sgl/sgl_pch.h
sgl/include/sgl/app/app.h
sgl/include/sgl/core/bitmap.h
sgl/include/sgl/core/crypto.h
sgl/include/sgl/core/data_type.h
sgl/include/sgl/core/dds_file.h
sgl/include/sgl/core/enum.h
sgl/include/sgl/core/error.h
sgl/include/sgl/core/file_stream.h
sgl/include/sgl/core/file_system_watcher.h
sgl/include/sgl/core/format.h
sgl/include/sgl/core/fwd.h
sgl/include/sgl/core/hash.h
sgl/include/sgl/core/input.h
sgl/include/sgl/core/logger.h
sgl/include/sgl/core/macros.h
sgl/include/sgl/core/maths.h
sgl/include/sgl/core/memory_mapped_file.h
sgl/include/sgl/core/memory_mapped_file_stream.h
sgl/include/sgl/core/memory_stream.h
sgl/include/sgl/core/object.h
sgl/include/sgl/core/platform.h
sgl/include/sgl/core/plugin.h
sgl/include/sgl/core/resolver.h
sgl/include/sgl/core/short_vector.h
sgl/include/sgl/core/static_vector.h
sgl/include/sgl/core/stream.h
sgl/include/sgl/core/string.h
sgl/include/sgl/core/struct.h
sgl/include/sgl/core/thread.h
sgl/include/sgl/core/timer.h
sgl/include/sgl/core/traits.h
sgl/include/sgl/core/type_utils.h
sgl/include/sgl/core/window.h
sgl/include/sgl/device/agility_sdk.h
sgl/include/sgl/device/blit.h
sgl/include/sgl/device/buffer_cursor.h
sgl/include/sgl/device/command.h
sgl/include/sgl/device/coopvec.h
sgl/include/sgl/device/cuda_interop.h
sgl/include/sgl/device/cuda_utils.h
sgl/include/sgl/device/cursor_utils.h
sgl/include/sgl/device/device.h
sgl/include/sgl/device/device_resource.h
sgl/include/sgl/device/fence.h
sgl/include/sgl/device/formats.h
sgl/include/sgl/device/fwd.h
sgl/include/sgl/device/helpers.h
nv_sgl-0.15.0.dist-info/METADATA
nv_sgl-0.15.0.dist-info/WHEEL
nv_sgl-0.15.0.dist-info/top_level.txt
nv_sgl-0.15.0.dist-info/RECORD
