Metadata-Version: 2.4
Name: nv-sgl
Version: 0.15.0
Summary: Slang Graphics Library
Home-page: https://github.com/shader-slang/sgl
Author: Simon Kallweit
Author-email: skallweit@nvidia.com
License: Apache-2.0
Requires-Python: >=3.9
License-File: LICENSE
Dynamic: author
Dynamic: author-email
Dynamic: description
Dynamic: description-content-type
Dynamic: home-page
Dynamic: license
Dynamic: license-file
Dynamic: requires-python
Dynamic: summary
